aqora_cli/__init__.py
aqora_cli/_aqora_cli.abi3.so
aqora_cli/_aqora_cli.pyi
aqora_cli/fsspec.py
aqora_cli/py.typed
aqora_cli/pyarrow.py
aqora_cli-0.22.0.dist-info/METADATA
aqora_cli-0.22.0.dist-info/WHEEL
aqora_cli-0.22.0.dist-info/entry_points.txt
aqora_cli-0.22.0.dist-info/RECORD
