Metadata-Version: 2.4
Name: aqora-cli
Version: 0.22.0
Requires-Dist: typing-extensions>=4.13.2
Requires-Dist: uv>=0.3.2,<1.0.0
Requires-Dist: fsspec>=2025.3.0 ; extra == 'fsspec'
Requires-Dist: fsspec>=2025.3.0 ; extra == 'pyarrow'
Requires-Dist: pyarrow>=17.0.0 ; extra == 'pyarrow'
Requires-Dist: build>=1.2.0,<2.0.0 ; extra == 'venv'
Requires-Dist: setuptools>=61.0 ; extra == 'venv'
Requires-Dist: ujson>=5.9.0,<6.0.0 ; extra == 'venv'
Requires-Dist: jupyterlab>=4.2.1,<5.0.0 ; extra == 'venv'
Requires-Dist: ipykernel>=6.29.4,<7.0.0 ; extra == 'venv'
Requires-Dist: nbconvert>=7.16.4,<8.0.0 ; extra == 'venv'
Requires-Dist: nbformat>=5.10.4,<6.0.0 ; extra == 'venv'
Provides-Extra: fsspec
Provides-Extra: pyarrow
Provides-Extra: venv
Summary: The aqora command line interface
Author-email: "S.A.S Aqora Quantum" <hello@aqora.io>
Requires-Python: >=3.8
Project-URL: Documentation, https://github.com/aqora-io/cli
Project-URL: Repository, https://github.com/aqora-io/cli
